interactivity/__init__.py
interactivity/exceptions.py
interactivity/generics.py
interactivity/actions/__init__.py
interactivity/actions/factories.py
interactivity/actions/handlers.py
interactivity/actions/payloads.py
interactivity/commands/__init__.py
interactivity/commands/exceptions.py
interactivity/commands/factories.py
interactivity/commands/handlers.py
interactivity/commands/payloads.py
interactivity/views/__init__.py
interactivity/views/factories.py
interactivity/views/handlers.py
interactivity/views/payloads.py
tests/__init__.py
tests/test_exceptions.py
tests/test_generics.py
tests/commands/__init__.py
tests/commands/conftest.py
tests/commands/test_exceptions.py
tests/commands/test_factories.py
tests/commands/test_handlers.py
tests/test_actions/__init__.py
tests/test_actions/conftest.py
tests/test_actions/test_factories.py
tests/test_actions/test_handlers.py
tests/test_views/__init__.py
tests/test_views/conftest.py
tests/test_views/test_factories.py
tests/test_views/test_handlers.py
slacktools_interactivity-1.2.1.dist-info/LICENSE
slacktools_interactivity-1.2.1.dist-info/METADATA
slacktools_interactivity-1.2.1.dist-info/WHEEL
slacktools_interactivity-1.2.1.dist-info/top_level.txt
slacktools_interactivity-1.2.1.dist-info/RECORD
