Metadata-Version: 2.1
Name: slacktools-interactivity
Version: 1.2.1
Summary: UNKNOWN
Home-page: https://github.com/danpoland/slacktools-interactivity
Author: Daniel Poland
Author-email: dan@crispy.dev
License: UNKNOWN
Platform: UNKNOWN
Classifier: Programming Language :: Python :: 3
Classifier: License :: OSI Approved :: MIT License
Classifier: Operating System :: OS Independent
Requires-Python: >=3.6
